.editorconfig
AUTHORS.rst
CHANGES.rst
LICENSE
README.rst
pytest.ini
setup.cfg
setup.py
pytest_testrail_client/__init__.py
pytest_testrail_client/_category.py
pytest_testrail_client/_enums.py
pytest_testrail_client/_exception.py
pytest_testrail_client/_session.py
pytest_testrail_client/_utils.py
pytest_testrail_client/helper.py
pytest_testrail_client/pytest_testrail_client.py
pytest_testrail_client/testrail_api.py
pytest_testrail_client.egg-info/PKG-INFO
pytest_testrail_client.egg-info/SOURCES.txt
pytest_testrail_client.egg-info/dependency_links.txt
pytest_testrail_client.egg-info/entry_points.txt
pytest_testrail_client.egg-info/requires.txt
pytest_testrail_client.egg-info/top_level.txt
pytest_testrail_client/model/__init__.py
pytest_testrail_client/model/case.py
pytest_testrail_client/model/case_type.py
pytest_testrail_client/model/plan.py
pytest_testrail_client/model/priority.py
pytest_testrail_client/model/project.py
pytest_testrail_client/model/result.py
pytest_testrail_client/model/run.py
pytest_testrail_client/model/section.py
pytest_testrail_client/model/status.py
pytest_testrail_client/model/suite.py
pytest_testrail_client/model/templates.py
pytest_testrail_client/model/test.py